st_rating_df/__init__.py
st_rating_df/frontend/build/asset-manifest.json
st_rating_df/frontend/build/bootstrap.min.css
st_rating_df/frontend/build/index.html
st_rating_df/frontend/build/precache-manifest.3bb8812f272f3b1b75b85c5bf7b56883.js
st_rating_df/frontend/build/service-worker.js
st_rating_df/frontend/build/static/js/2.c8c7ea18.chunk.js
st_rating_df/frontend/build/static/js/2.c8c7ea18.chunk.js.LICENSE.txt
st_rating_df/frontend/build/static/js/2.c8c7ea18.chunk.js.map
st_rating_df/frontend/build/static/js/main.212f7ebc.chunk.js
st_rating_df/frontend/build/static/js/main.212f7ebc.chunk.js.map
st_rating_df/frontend/build/static/js/runtime-main.b44bff0a.js
st_rating_df/frontend/build/static/js/runtime-main.b44bff0a.js.map
st_rating_df-0.0.10.dist-info/LICENSE
st_rating_df-0.0.10.dist-info/METADATA
st_rating_df-0.0.10.dist-info/WHEEL
st_rating_df-0.0.10.dist-info/top_level.txt
st_rating_df-0.0.10.dist-info/RECORD
