Metadata-Version: 2.1
Name: st-rating-df
Version: 0.0.10
Summary: UNKNOWN
Home-page: UNKNOWN
Author: Anton Buch
Author-email: anton.buch@bayer.com
License: MIT License
Platform: UNKNOWN
Requires-Python: >=3.6
License-File: LICENSE
Requires-Dist: streamlit (>=0.63)
Requires-Dist: pandas (>=1.3)
Requires-Dist: numpy (>=1.20)
